jupiter_decoder/__init__.py
jupiter_decoder/account_info_manager.py
jupiter_decoder/event_static_methods.py
jupiter_decoder/instruction_static_methods.py
jupiter_decoder/jup_event_parser.py
jupiter_decoder/jup_rpc_client.py
jupiter_decoder/sessions.py
jupiter_decoder/contracts/__init__.py
jupiter_decoder/contracts/consts.py
jupiter_decoder/contracts/errors.py
jupiter_decoder/contracts/fee_config.py
jupiter_decoder/contracts/idl_json.py
jupiter_decoder/contracts/logger.py
jupiter_decoder/contracts/parsed_event.py
jupiter_decoder/contracts/parsed_fee_event.py
jupiter_decoder/contracts/parsed_swap_event.py
jupiter_decoder/contracts/route_info.py
jupiter_decoder/contracts/swap.py
jupiter_decoder/contracts/swap_attributes.py
jupiter_decoder/contracts/transfer_instructions.py
py_jup_decoder-0.1.4.dist-info/METADATA
py_jup_decoder-0.1.4.dist-info/WHEEL
py_jup_decoder-0.1.4.dist-info/top_level.txt
py_jup_decoder-0.1.4.dist-info/RECORD
